risingwave_connect/__init__.py
risingwave_connect/client.py
risingwave_connect/connect_builder.py
risingwave_connect/models.py
risingwave_connect/discovery/__init__.py
risingwave_connect/discovery/base.py
risingwave_connect/sinks/__init__.py
risingwave_connect/sinks/base.py
risingwave_connect/sinks/iceberg.py
risingwave_connect/sinks/postgresql.py
risingwave_connect/sinks/s3.py
risingwave_connect/sources/__init__.py
risingwave_connect/sources/mongodb.py
risingwave_connect/sources/postgresql.py
risingwave_connect_py-0.3.0.dist-info/METADATA
risingwave_connect_py-0.3.0.dist-info/WHEEL
risingwave_connect_py-0.3.0.dist-info/licenses/LICENSE
risingwave_connect_py-0.3.0.dist-info/RECORD
