Metadata-Version: 2.4
Name: risingwave-connect-py
Version: 0.3.0
Summary: Python SDK for integrating RisingWave with various CDC sources (like PostgreSQL, MongoDB) and supporting multiple sink destinations such as Iceberg and S3.
Project-URL: Homepage, https://github.com/risingwavelabs/risingwave-connect-py
Project-URL: Repository, https://github.com/risingwavelabs/risingwave-connect-py
Project-URL: Issues, https://github.com/risingwavelabs/risingwave-connect-py/issues
Author-email: Yuxuan Liao <yuxuan@risingwave-labs.com>
License-Expression: Apache-2.0
License-File: LICENSE
Keywords: cdc,data-connector,iceberg,mongodb,postgresql,risingwave,risingwave-connect,risingwave-connect-py,risingwave_connect,risingwave_connect_py,s3,streaming
Classifier: Development Status :: 4 - Beta
Classifier: Intended Audience :: Developers
Classifier: License :: OSI Approved :: Apache Software License
Classifier: Operating System :: OS Independent
Classifier: Programming Language :: Python :: 3
Classifier: Programming Language :: Python :: 3.10
Classifier: Programming Language :: Python :: 3.11
Classifier: Programming Language :: Python :: 3.12
Classifier: Topic :: Database
Classifier: Topic :: Software Development :: Libraries :: Python Modules
Requires-Python: >=3.10
Requires-Dist: psycopg[binary]>=3.1
Requires-Dist: pydantic>=2.7
Requires-Dist: pymongo>=4.0
